tree_explorer/__init__.py
tree_explorer/base/__init__.py
tree_explorer/explorers/__init__.py
tree_explorer/test/__init__.py
tree_explorer/test/test_explorer.py
tree_explorer/test/test_rf_explorer.py
tree_explorer/test/test_tree_explorer.py
tree_explorer/utils/__init__.py
tree_explorer/utils/metaestimators.py
tree_explorer/utils/test.py
tree_explorer/utils/validation.py
tree_explorer-0.0.1.dist-info/LICENSE
tree_explorer-0.0.1.dist-info/METADATA
tree_explorer-0.0.1.dist-info/WHEEL
tree_explorer-0.0.1.dist-info/top_level.txt
tree_explorer-0.0.1.dist-info/RECORD
